{
  "code": 0,
  "message": "",
  "data": [
    {
      "label": "Linux 实操",
      "list": [
        {
          "title": "如何查找 /data/log/ 目录中超过30天的文件并删除",
          "reference": ""
        },
        {
          "title": "主机开放了一个 7821 端口，如何获知此端口是哪个程序开启的？",
          "reference": ""
        },
        {
          "title": "写一个周期性的计划任务，每4小时执行一次对 /etc 目录的备份，备份保存到 /data/backup 目录中，保存的文件名形如 etc-2020072108.tgz",
          "reference": ""
        },
        {
          "title": "写出在 Centos6 或 Centos7 系统中添加一个硬盘的步骤。",
          "reference": ""
        },
        {
          "title": "请使用 sed 命令替换 /etc/inittab 文件中 “id:3:initdefault:” 一行中的数字3为数字5",
          "reference": ""
        }
      ]
    },
    {
      "label": "故障排查",
      "list": [
        {
          "title": "如果有人电脑连不上网，你会怎么排查问题？",
          "reference": ""
        },
        {
          "title": "如果一台机器被执行了挖矿脚本，应该怎么排查问题。",
          "reference": ""
        },
        {
          "title": "假如现在有一套 LNMP 架构的系统，访问非常缓慢，你会从什么方向开始调查。",
          "reference": ""
        }
      ]
    },
    {
      "label": "网络协议理解",
      "list": [
        {
          "title": "请用自己的语言详细描述一下 CDN 在网络过程中的原理及作用。",
          "reference": ""
        },
        {
          "title": "请结合自己的认识给出提升云主机安全性的思路。",
          "reference": ""
        }
      ]
    },
    {
      "label": "监控系统理解",
      "list": [
        {
          "title": "如果目前有20台机器，每台机器上有多套 LNMP 结构的系统，你会怎样收集 NGINX 的日志并监控其运行状态。",
          "reference": ""
        },
        {
          "title": "用过哪些监控组件，你是怎样监控线上服务并预警的？",
          "reference": ""
        },
        {
          "title": "用自己的语言简单描述一下 ELK 这套架构，每个部件的功能、数据流动、性能瓶颈等。",
          "reference": ""
        }
      ]
    },
    {
      "label": "实施流程理解和规范",
      "list": [
        {
          "title": "以前后端分离的项目为例，你会怎样设计一套安全的代码上线流程，提示：注意前后端的区别、CI/CD、保障措施。",
          "reference": ""
        },
        {
          "title": "当公司需要使用一项云产品，如：cdn、云主机、负载均衡器、云函数等 ，你会怎么估算用量其费用。",
          "reference": ""
        }
      ]
    }
  ]
}